pymodm/__init__.py
pymodm/common.py
pymodm/compat.py
pymodm/connection.py
pymodm/context_managers.py
pymodm/dereference.py
pymodm/errors.py
pymodm/fields.py
pymodm/files.py
pymodm/manager.py
pymodm/queryset.py
pymodm/validators.py
pymodm/vendor.py
pymodm/base/__init__.py
pymodm/base/fields.py
pymodm/base/models.py
pymodm/base/options.py
pymodm-0.4.3.dist-info/METADATA
pymodm-0.4.3.dist-info/WHEEL
pymodm-0.4.3.dist-info/top_level.txt
pymodm-0.4.3.dist-info/RECORD
