Metadata-Version: 2.1
Name: pymodm
Version: 0.4.3
Summary: PyMODM is a generic ODM on top of PyMongo.
Home-page: UNKNOWN
Author: Luke Lovett
Author-email: mongodb-user@googlegroups.com
License: Apache License, Version 2.0
Platform: any
Classifier: Development Status :: 3 - Alpha
Classifier: Intended Audience :: Developers
Classifier: License :: OSI Approved :: Apache Software License
Classifier: Operating System :: OS Independent
Classifier: Programming Language :: Python
Classifier: Programming Language :: Python :: 2.7
Classifier: Programming Language :: Python :: 3
Classifier: Programming Language :: Python :: 3.3
Classifier: Programming Language :: Python :: 3.4
Classifier: Programming Language :: Python :: 3.5
Classifier: Programming Language :: Python :: 3.6
Classifier: Programming Language :: Python :: 3.7
Classifier: Programming Language :: Python :: 3.8
Classifier: Programming Language :: Python :: Implementation :: CPython
Classifier: Programming Language :: Python :: Implementation :: PyPy
Classifier: Topic :: Database
Classifier: Topic :: Software Development :: Libraries :: Python Modules
Requires-Dist: pymongo (<4.0,>=3.4)
Requires-Dist: ipaddress
Provides-Extra: images
Requires-Dist: Pillow ; extra == 'images'
